h3sed/__init__.py
h3sed/__main__.py
h3sed/conf.py
h3sed/gui.py
h3sed/guibase.py
h3sed/images.py
h3sed/main.py
h3sed/metadata.py
h3sed/templates.py
h3sed/etc/h3sed.ini
h3sed/hero/__init__.py
h3sed/hero/army.py
h3sed/hero/equipment.py
h3sed/hero/gui.py
h3sed/hero/inventory.py
h3sed/hero/skills.py
h3sed/hero/spells.py
h3sed/hero/stats.py
h3sed/lib/__init__.py
h3sed/lib/controls.py
h3sed/lib/util.py
h3sed/lib/wx_accel.py
h3sed/version/__init__.py
h3sed/version/ab.py
h3sed/version/hc.py
h3sed/version/hota.py
h3sed/version/roe.py
h3sed/version/sod.py
h3sed-3.3.dist-info/licenses/LICENSE.md
h3sed-3.3.dist-info/METADATA
h3sed-3.3.dist-info/WHEEL
h3sed-3.3.dist-info/entry_points.txt
h3sed-3.3.dist-info/top_level.txt
h3sed-3.3.dist-info/RECORD
