Metadata-Version: 2.4
Name: h3sed
Version: 3.3
Summary: Heroes3 Savegame Editor
Home-page: https://github.com/suurjaak/h3sed
Author: Erki Suurjaak
Author-email: erki@lap.ee
License: MIT
Keywords: homm homm3 heroes3 savegame
Platform: any
Classifier: Development Status :: 5 - Production/Stable
Classifier: Intended Audience :: End Users/Desktop
Classifier: Operating System :: Microsoft :: Windows
Classifier: Operating System :: Unix
Classifier: Operating System :: MacOS
Classifier: Topic :: Games/Entertainment
Classifier: Topic :: Utilities
Classifier: Topic :: Desktop Environment
Classifier: License :: OSI Approved :: MIT License
Classifier: Programming Language :: Python :: 2
Classifier: Programming Language :: Python :: 2.7
Classifier: Programming Language :: Python :: 3
License-File: LICENSE.md
Requires-Dist: pyyaml
Requires-Dist: step-template>=0.0.4
Requires-Dist: wxPython>=4.0
Dynamic: author
Dynamic: author-email
Dynamic: classifier
Dynamic: description
Dynamic: description-content-type
Dynamic: home-page
Dynamic: keywords
Dynamic: license
Dynamic: license-file
Dynamic: platform
Dynamic: requires-dist
Dynamic: summary
